setup.py
getresponse/__init__.py
getresponse/account.py
getresponse/campaign.py
getresponse/client.py
getresponse/contact.py
getresponse/enums.py
getresponse/excs.py
getresponse.egg-info/PKG-INFO
getresponse.egg-info/SOURCES.txt
getresponse.egg-info/dependency_links.txt
getresponse.egg-info/not-zip-safe
getresponse.egg-info/requires.txt
getresponse.egg-info/top_level.txt