Metadata-Version: 1.0
Name: getresponse
Version: 0.1
Summary: Email Marketing Software
Home-page: https://bitbucket.org/ingmferrer/getresponse-python
Author: Miguel Ferrer
Author-email: ingferrermiguel@gmail.com
License: MIT
Platform: UNKNOWN
